krx_competition_37/__init__.py
krx_competition_37-1.0.0.dist-info/METADATA
krx_competition_37-1.0.0.dist-info/WHEEL
krx_competition_37-1.0.0.dist-info/top_level.txt
krx_competition_37-1.0.0.dist-info/RECORD
