Metadata-Version: 2.1
Name: krx-competition-37
Version: 1.0.0
Summary: krx_competition_37
Home-page: 
Author: sjyoo
Author-email: 
Requires-Python: >=3.10
